pyspiceworks/Spiceworks.py
pyspiceworks/__init__.py
pyspiceworks/example.py
pyspiceworks-0.0.0a1.dist-info/LICENSE.md
pyspiceworks-0.0.0a1.dist-info/METADATA
pyspiceworks-0.0.0a1.dist-info/WHEEL
pyspiceworks-0.0.0a1.dist-info/top_level.txt
pyspiceworks-0.0.0a1.dist-info/RECORD
